README.rst
mcrcon.py
setup.py
mcrcon.egg-info/PKG-INFO
mcrcon.egg-info/SOURCES.txt
mcrcon.egg-info/dependency_links.txt
mcrcon.egg-info/top_level.txt