Metadata-Version: 1.1
Name: mcrcon
Version: 0.5.1
Summary: A client for handling Remote Commands (RCON) to a Minecraft server.
Home-page: https://github.com/uncaught-exceptions/mcrcon
Author: Adrian Turjak
Author-email: minecraft@uncaught-exceptions.com
License: MIT
Keywords: openstack keystone users tasks registration workflow
Platform: UNKNOWN
Classifier: Development Status :: 5 - Production/Stable
Classifier: Intended Audience :: Developers
Classifier: Intended Audience :: System Administrators
Classifier: License :: OSI Approved :: MIT License
Classifier: Programming Language :: Python :: 2.7
Classifier: Programming Language :: Python :: 3.6
